cardbuilder/__init__.py
cardbuilder/exceptions.py
cardbuilder/common/__init__.py
cardbuilder/common/config.py
cardbuilder/common/util.py
cardbuilder/input/__init__.py
cardbuilder/input/input_list.py
cardbuilder/input/instantiable.py
cardbuilder/input/word.py
cardbuilder/input/word_list.py
cardbuilder/input/en/__init__.py
cardbuilder/input/en/svl.py
cardbuilder/lookup/__init__.py
cardbuilder/lookup/data_source.py
cardbuilder/lookup/instantiable.py
cardbuilder/lookup/lookup_data.py
cardbuilder/lookup/tatoeba.py
cardbuilder/lookup/value.py
cardbuilder/lookup/en/__init__.py
cardbuilder/lookup/en/merriam_webster.py
cardbuilder/lookup/en/word_freq.py
cardbuilder/lookup/en_to_ja/__init__.py
cardbuilder/lookup/en_to_ja/eijiro.py
cardbuilder/lookup/en_to_ja/ejdict_hand.py
cardbuilder/lookup/en_to_ja/gene_dict.py
cardbuilder/lookup/eo/__init__.py
cardbuilder/lookup/eo/simpla_vortaro.py
cardbuilder/lookup/eo_to_en/__init__.py
cardbuilder/lookup/eo_to_en/espdic.py
cardbuilder/lookup/he_to_en/__init__.py
cardbuilder/lookup/ja/__init__.py
cardbuilder/lookup/ja/nhk_pitch_accent.py
cardbuilder/lookup/ja/ojad.py
cardbuilder/lookup/ja_to_en/__init__.py
cardbuilder/lookup/ja_to_en/jisho.py
cardbuilder/resolution/__init__.py
cardbuilder/resolution/anki.py
cardbuilder/resolution/card_data.py
cardbuilder/resolution/delimited.py
cardbuilder/resolution/field.py
cardbuilder/resolution/instantiable.py
cardbuilder/resolution/printer.py
cardbuilder/resolution/resolution_engine.py
cardbuilder/resolution/resolver.py
cardbuilder/resources/anki/cardstyle.css
cardbuilder/resources/anki/en_to_ja/def_card_back.html
cardbuilder/resources/anki/en_to_ja/def_card_front.html
cardbuilder/resources/anki/en_to_ja/word_card_back.html
cardbuilder/resources/anki/en_to_ja/word_card_front.html
cardbuilder/resources/anki/eo_to_en/def_card_back.html
cardbuilder/resources/anki/eo_to_en/def_card_front.html
cardbuilder/resources/anki/eo_to_en/word_card_back.html
cardbuilder-0.0.26.dist-info/LICENSE
cardbuilder-0.0.26.dist-info/METADATA
cardbuilder-0.0.26.dist-info/WHEEL
cardbuilder-0.0.26.dist-info/entry_points.txt
cardbuilder-0.0.26.dist-info/top_level.txt
cardbuilder-0.0.26.dist-info/RECORD
