Metadata-Version: 2.1
Name: cardbuilder
Version: 0.0.26
Summary: A package for programmatically generating language learning flashcards
Home-page: https://github.com/Mindful/cardbuilder
Author: Joshua Tanner
Author-email: mindful.jt@gmail.com
License: UNKNOWN
Keywords: flashcards,ankilanguage learning
Platform: UNKNOWN
Classifier: Programming Language :: Python :: 3
Classifier: License :: OSI Approved :: MIT License
Classifier: Operating System :: OS Independent
Requires-Python: >=3.6
License-File: LICENSE
Requires-Dist: requests (~=2.25.1)
Requires-Dist: lxml (~=4.6.2)
Requires-Dist: genanki (~=0.10.1)
Requires-Dist: tqdm (~=4.56.0)
Requires-Dist: pykakasi (~=2.0.6)
Requires-Dist: unidic-lite (~=1.0.8)
Requires-Dist: fugashi (~=1.1.0)
Requires-Dist: retry (~=0.9.2)
Requires-Dist: spacy (~=3.0.5)
Requires-Dist: beautifulsoup4 (~=4.9.3)
